Workbook
Name array: Table1[[Item description]:[Customer Contact No.]]
Name Bocaue: INDIRECT!$J$18:$J$20
Name Bulacan: INDIRECT!$H$5:$H$7
Name Cubao: INDIRECT!$E$18:$E$19
Name Fairview: INDIRECT!$F$18:$F$19
Name inv: Table1[Invoice No.]
Name Lazaro: INDIRECT!$K$18:$K$20
Name Marilao: INDIRECT!$I$18:$I$20
Name Maynila: INDIRECT!$I$5:$I$7
Name Megamall: INDIRECT!$L$18:$L$20
Name Payments: #REF!
Name QuezonCity: INDIRECT!$G$5:$G$7
Name Status: #REF!
Name Trinoma: INDIRECT!$G$18:$G$19
Name Tungko: INDIRECT!$H$18:$H$19

Sheet INDIRECT
B2: MULTIPLE DEPENDENT DROP-DOWN | G2: Branch Per City
B4: City | C4: Branch | D4: Employee name | G4: QuezonCity | H4: Bulacan | I4: Maynila
B5: Maynila | C5: Lazaro | D5: Mark | G5: Cubao | H5: Tungko | I5: Lazaro
G6: Fairview | H6: Marilao | I6: Megamall
G7: Trinoma | H7: Bocaue
G14: Employee name Per Branch
E16: Quezon City | H16: Bulacan | K16: Maynila
E17: Cubao | F17: Fairview | G17: Trinoma | H17: Tungko | I17: Marilao | J17: Bocaue | K17: Lazaro | L17: Megamall
E18: Julie | F18: Fred | G18: Suzette | H18: Baste | I18: Jayr | J18: Cardo | K18: Nina | L18: Carol
E19: Bogart | G19: Ronald | H19: Junie | I19: Rustom | K19: Mark
I20: Michael

Sheet Customer Data
B2: Customer Data
B4: Invoice No. | C4: Item description | D4: Qty | E4: Unit Price | F4: Cashier | G4: Transaction Type | H4: Customer Contact No.
B5: 20201 | C5: Cookware Set | D5: 2 | E5: 3200 | F5: Kim | G5: Card | H5: 908122312121
B6: 20202 | C6: Cookware Set | D6: 3 | E6: 3200 | F6: Andrea | G6: Cash | H6: 909012121221
B7: 20203 | C7: Cookware Set | D7: 1 | E7: 3200 | F7: Michelle | G7: Card | H7: 905123712878
B8: 20204 | C8: Cookware Set | D8: 6 | E8: 3200 | F8: Joseph | G8: Card | H8: 999992131311
B9: 20205 | C9: Cookware Set | D9: 7 | E9: 3200 | F9: Aira | G9: Card | H9: 956128179797
B10: 20206 | C10: Cookware Set | D10: 4 | E10: 3200 | F10: Joel | G10: Cash | H10: 971233363444
B11: 20201 | C11: Dinner Set | D11: 5 | E11: 2500 | F11: Kim | G11: Card | H11: 908122312121
B12: 20201 | C12: Dining Table | D12: 1 | E12: 15000 | F12: Kim | G12: Card | H12: 908122312121
B13: 20202 | C13: Foldable Table | D13: 16 | E13: 2200 | F13: Andrea | G13: Cash | H13: 909012121221
B14: 20202 | C14: Lamp | D14: 20 | E14: 1200 | F14: Andrea | G14: Cash | H14: 909012121221
B15: 20202 | C15: Outdoor Firepit | D15: 5 | E15: 2300 | F15: Andrea | G15: Cash | H15: 909012121221
B16: 20204 | C16: Dinner Set | D16: 15 | E16: 2500 | F16: Joseph | G16: Card | H16: 999992131311
... B25: 20201 | C25: Side Table | D25: 20 | E25: 1800 | F25: KIM | G25: Card | H25: 971233363444

Sheet Xlookup & Sumifs
B5: Employee Name | C5: Nash | E5: Total Sales
B6: Product Sold | C6: Laptop | E6: =SUMIFS(_xlfn.XLOOKUP(C7,Table14[[#Headers],[Market-Market]:[Up-Town]],D11:G21),B11:B21,C5,C11:C21,C6) -> 50009
B7: Branch | C7: Pasay
D9: Sales Per Branch
B10: Employee Name | C10: Product Sold | D10: Market-Market | E10: Fairview | F10: Pasay | G10: Up-Town
B11: Gilbert | C11: Laptop | D11: 50000 | E11: 60000 | F11: 35000 | G11: 25000
B12: RoseMarie | C12: Printer | D12: 45000 | E12: 45001 | F12: 45002 | G12: 45003
B13: Nash | C13: Printer | D13: 3000 | E13: 3001 | F13: 3002 | G13: 3003
B14: Francis | C14: Mouse | D14: 2500 | E14: 2501 | F14: 2502 | G14: 2503
B15: Malou | C15: Keyboard | D15: 5000 | E15: 5001 | F15: 5002 | G15: 5003
B16: Jay-r | C16: Keyboard | D16: 11000 | E16: 11001 | F16: 11002 | G16: 11003
B17: Gilbert | C17: Laptop | D17: 25000 | E17: 25001 | F17: 25002 | G17: 25003
B18: Nash | C18: Case | D18: 3500 | E18: 3500 | F18: 3500 | G18: 3500
B19: Nash | C19: Case | D19: 4500 | E19: 4500 | F19: 4500 | G19: 4500
B20: Nash | C20: Laptop | D20: 50009 | E20: 50009 | F20: 50009 | G20: 50009
B21: Jay-r | C21: Mouse | D21: 8000 | E21: 8000 | F21: 8000 | G21: 8000

Sheet Shipped Tracker
B3: Logistics Tracker | H3: Completion
B5: Item ID | C5: Location | D5: Order Qty | E5: Remarks | H5: Item ID | I5: Location | J5: Order Qty | K5: Remarks
B6: 1001 | C6: Pasay | D6: 280 | E6: Pending | H6: 1011 | I6: Cotabato | J6: 99 | K6: Shipped
B7: 1002 | C7: Bocaue | D7: 78 | E7: Pending | H7: 1009 | I7: Ozamis | J7: 670 | K7: Shipped
B8: 1004 | C8: Marilao | D8: 160 | E8: Pending | H8: 1006 | I8: Paranaque | J8: 277 | K8: Shipped
B9: 1005 | C9: Mandaluyong | D9: 131 | E9: Pending | H9: 1003 | I9: Malolos | J9: 31 | K9: Shipped
B10: 1007 | C10: Cubao | D10: 566 | E10: Pending | H10: 1008 | I10: Cavite | J10: 900 | K10: Shipped
B11: 1010 | C11: Tagbilaran | D11: 540 | E11: Pending

Sheet FILTER
B2: KURT FURNITURE CO. | E2: INVOICE
B3: Jeddah, Saudi Arabia
B4: Bawadi District.
B5: Phone: (516) 555-0135
B7: CASHIER | E7: INVOICE # | F7: DATE
B8: =IFERROR(_xlfn.XLOOKUP(E8,'Customer Data'!B:B,'Customer Data'!F:F),"") -> Andrea | E8: 20202 | F8: =TODAY() -> 46276
E10: CUSTOMER NO. | F10: TRANSACTION TYPE
E11: =IFERROR(_xlfn.XLOOKUP(E8,'Customer Data'!B:B,'Customer Data'!H:H),"") -> 909012121221 | F11: =IFERROR(_xlfn.XLOOKUP(E8,'Customer Data'!B:B,'Customer Data'!G:G),"") -> Cash
B15: ITEM DESCRIPTION | D15: QTY | E15: UNIT PRICE | F15: AMOUNT
B16: {=_xlfn._xlws.FILTER('Customer Data'!B5:E25,'Customer Data'!B5:B25=FILTER!E8)} -> 20202 | C16: Cookware Set | D16: 3 | E16: 3200 | F16: =IF(D16="",ROUND(1*E16,2),ROUND(D16*E16,2)) -> 9600
B17: 20202 | C17: Foldable Table | D17: 16 | E17: 2200 | F17: =IF(D17="",ROUND(1*E17,2),ROUND(D17*E17,2)) -> 35200
B18: 20202 | C18: Lamp | D18: 20 | E18: 1200 | F18: =IF(D18="",ROUND(1*E18,2),ROUND(D18*E18,2)) -> 24000
B19: 20202 | C19: Outdoor Firepit | D19: 5 | E19: 2300 | F19: =IF(D19="",ROUND(1*E19,2),ROUND(D19*E19,2)) -> 11500
F20: =IF(D20="",ROUND(1*E20,2),ROUND(D20*E20,2)) -> 0
F21: =IF(D21="",ROUND(1*E21,2),ROUND(D21*E21,2)) -> 0
F22: =IF(D22="",ROUND(1*E22,2),ROUND(D22*E22,2)) -> 0
F23: =IF(D23="",ROUND(1*E23,2),ROUND(D23*E23,2)) -> 0
F24: =IF(D24="",ROUND(1*E24,2),ROUND(D24*E24,2)) -> 0
F25: =IF(D25="",ROUND(1*E25,2),ROUND(D25*E25,2)) -> 0
F26: =IF(D26="",ROUND(1*E26,2),ROUND(D26*E26,2)) -> 0
F27: =IF(D27="",ROUND(1*E27,2),ROUND(D27*E27,2)) -> 0
F28: =IF(D28="",ROUND(1*E28,2),ROUND(D28*E28,2)) -> 0
F29: =IF(D29="",ROUND(1*E29,2),ROUND(D29*E29,2)) -> 0
F30: =IF(D30="",ROUND(1*E30,2),ROUND(D30*E30,2)) -> 0
B31: Thank you for your business! | D31: SUBTOTAL | F31: =SUM(F16:F30) -> 80300
D32: TAX RATE | F32: 0.0425
D33: TAX | F33: =F31*F32 -> 3412.75
D34: TOTAL | F34: =F31+F33 -> 83712.75
B37: If you have any questions about this invoice, please contact
B38: KURT CREATES EXCEL TRICKS & TUTORIALS

Sheet AUTOFILTER
B5: Customer Data
B7: Invoice No. | C7: Item description | D7: Qty | E7: Unit Price | F7: Cashier | G7: Transaction Type | H7: Customer Contact No.
C8: {=_xlfn._xlws.FILTER(array,inv=A1,"not found")} -> not found

Sheet CHECKBOX
B2: Order Tracker
B4: Product | D4: Status
C5: In Progress | D5: Shipped | E5: Delivered | F5: Status
B6: Hair Blower | C6: TRUE | D6: TRUE | E6: TRUE | F6: =IF(AND(C6=TRUE,D6=TRUE,E6=TRUE),"Delivered",IF(AND(C6=TRUE,D6=TRUE),"Shipped",IF(C6=TRUE,"In Progress",""))) -> Delivered
B7: Lamp | C7: FALSE | D7: FALSE | E7: FALSE | F7: =IF(AND(C7=TRUE,D7=TRUE,E7=TRUE),"Delivered",IF(AND(C7=TRUE,D7=TRUE),"Shipped",IF(C7=TRUE,"In Progress","")))
B8: Vaccum | C8: TRUE | D8: TRUE | E8: FALSE | F8: =IF(AND(C8=TRUE,D8=TRUE,E8=TRUE),"Delivered",IF(AND(C8=TRUE,D8=TRUE),"Shipped",IF(C8=TRUE,"In Progress",""))) -> Shipped
B9: Tool-Kit | C9: TRUE | D9: TRUE | E9: TRUE | F9: =IF(AND(C9=TRUE,D9=TRUE,E9=TRUE),"Delivered",IF(AND(C9=TRUE,D9=TRUE),"Shipped",IF(C9=TRUE,"In Progress",""))) -> Delivered
B10: Hammer | C10: FALSE | D10: FALSE | E10: FALSE | F10: =IF(AND(C10=TRUE,D10=TRUE,E10=TRUE),"Delivered",IF(AND(C10=TRUE,D10=TRUE),"Shipped",IF(C10=TRUE,"In Progress","")))
B11: Razor | C11: TRUE | D11: FALSE | E11: FALSE | F11: =IF(AND(C11=TRUE,D11=TRUE,E11=TRUE),"Delivered",IF(AND(C11=TRUE,D11=TRUE),"Shipped",IF(C11=TRUE,"In Progress",""))) -> In Progress

Sheet ADVANCED VLOOKUP
B2: Purchase Data
B4: Invoice No. | C4: Item description | D4: Qty | E4: Unit Price | F4: Budget Cost | G4: Cashier
B5: 20201 | C5: Mechanical Keyboard | D5: 2 | E5: 3200 | F5: =SUM(Table15[[#This Row],[Qty]]*Table15[[#This Row],[Unit Price]]) -> 6400 | G5: Kim
B6: 20202 | C6: Mousepad | D6: 3 | E6: 600 | F6: =SUM(Table15[[#This Row],[Qty]]*Table15[[#This Row],[Unit Price]]) -> 1800 | G6: Andrea
B7: 20203 | C7: Headset | D7: 1 | E7: 1200 | F7: =SUM(Table15[[#This Row],[Qty]]*Table15[[#This Row],[Unit Price]]) -> 1200 | G7: Michelle
B8: 20204 | C8: Speakers | D8: 6 | E8: 2300 | F8: =SUM(Table15[[#This Row],[Qty]]*Table15[[#This Row],[Unit Price]]) -> 13800 | G8: Joseph
B9: 20205 | C9: Digital Clock | D9: 7 | E9: 1500 | F9: =SUM(Table15[[#This Row],[Qty]]*Table15[[#This Row],[Unit Price]]) -> 10500 | G9: Aira
B10: 20206 | C10: Gaming Mouse | D10: 4 | E10: 1300 | F10: =SUM(Table15[[#This Row],[Qty]]*Table15[[#This Row],[Unit Price]]) -> 5200 | G10: Joel
B16: Invoice No. | C16: Item description | D16: Qty | E16: Unit Price | F16: Budget Cost | G16: Cashier
B18: 20201 | C18: {=VLOOKUP(B18,Table15[#All],{2,3,4,5,6},0)} -> Mechanical Keyboard | D18: 2 | E18: 3200 | F18: 6400 | G18: Kim
B19: 20202 | C19: {=VLOOKUP(B19,Table15[#All],{2,3,4,5,6},0)} -> Mousepad | D19: 3 | E19: 600 | F19: 1800 | G19: Andrea
B20: 20203 | C20: {=VLOOKUP(B20,Table15[#All],{2,3,4,5,6},0)} -> Headset | D20: 1 | E20: 1200 | F20: 1200 | G20: Michelle
B21: 20204 | C21: {=VLOOKUP(B21,Table15[#All],{2,3,4,5,6},0)} -> Speakers | D21: 6 | E21: 2300 | F21: 13800 | G21: Joseph
B22: 20205 | C22: {=VLOOKUP(B22,Table15[#All],{2,3,4,5,6},0)} -> Digital Clock | D22: 7 | E22: 1500 | F22: 10500 | G22: Aira
B23: 20206 | C23: {=VLOOKUP(B23,Table15[#All],{2,3,4,5,6},0)} -> Gaming Mouse | D23: 4 | E23: 1300 | F23: 5200 | G23: Joel

Sheet Sales
B1: Sales Per Region
B3: ID | C3: Region | D3: Revenue
B4: 1001 | C4: Western | D4: 250000
B5: 1002 | C5: Central | D5: 550000
B6: 1003 | C6: Eastern | D6: 850000
B7: 1003 | C7: North | D7: 740000
B8: 1003 | C8: South | D8: 10000000

Sheet Profit
B1: Profit Per Region
B3: Region | C3: Profit
B4: Western | C4: =Sales!D4/2 -> 125000
B5: Central | C5: =Sales!D5/2 -> 275000
B6: Eastern | C6: =Sales!D6/2 -> 425000
B7: North | C7: =Sales!D7/2 -> 370000
B8: South | C8: =Sales!D8/2 -> 5000000

Sheet POWER PIVOT
B3: Region | C3: Sales | D3: Profit value | E3: Cost
B4: Central | C4: 550000 | D4: 275000 | E4: 1100000
B5: Eastern | C5: 850000 | D5: 425000 | E5: 1700000
B6: North | C6: 740000 | D6: 370000 | E6: 1480000
B7: South | C7: 10000000 | D7: 5000000 | E7: 20000000
B8: Western | C8: 250000 | D8: 125000 | E8: 500000
B9: Grand Total | C9: 12390000 | D9: 6195000 | E9: 24780000

Sheet Cost
B1: Budget Cost Per Region
B3: Region | C3: Budget Cost | D3: Product
B4: Western | C4: =Sales!D4*2 -> 500000 | D4: Gaming Consoles
B5: Central | C5: =Sales!D5*2 -> 1100000 | D5: Peripherals
B6: Eastern | C6: =Sales!D6*2 -> 1700000 | D6: System Units
B7: North | C7: =Sales!D7*2 -> 1480000 | D7: Gadgets
B8: South | C8: =Sales!D8*2 -> 20000000 | D8: Appliances

Sheet INDEX MATCH
C4: Revenue | J4: Product | K4: Furniture
C6: Product | D6: Pasay | E6: Market-Market | F6: Mandaluyong | G6: Cubao | H6: Valenzuela | J6: Branch | K6: Sales Per Branch
C7: Peripherals | D7: 45000 | E7: 115000 | F7: 180000 | G7: 120000 | H7: 90000 | J7: Pasay | K7: =INDEX($C$6:$H$11,MATCH($K$4,$C$6:$C$11,0),MATCH(J7,$C$6:$H$6,0)) -> 150000
C8: Furniture | D8: 150000 | E8: 116000 | F8: 45002 | G8: 78000 | H8: 45004 | J8: Market-Market | K8: =INDEX($C$6:$H$11,MATCH($K$4,$C$6:$C$11,0),MATCH(J8,$C$6:$H$6,0)) -> 116000
C9: Gadgets | D9: 117000 | E9: 45001 | F9: 99000 | G9: 66000 | H9: 87000 | J9: Mandaluyong | K9: =INDEX($C$6:$H$11,MATCH($K$4,$C$6:$C$11,0),MATCH(J9,$C$6:$H$6,0)) -> 45002
C10: Dinning Set | D10: 20000 | E10: 450000 | F10: 89000 | G10: 240000 | H10: 65000 | J10: Cubao | K10: =INDEX($C$6:$H$11,MATCH($K$4,$C$6:$C$11,0),MATCH(J10,$C$6:$H$6,0)) -> 78000
C11: Clothing | D11: 85000 | E11: 45001 | F11: 900000 | G11: 89000 | H11: 100000 | J11: Valenzuela | K11: =INDEX($C$6:$H$11,MATCH($K$4,$C$6:$C$11,0),MATCH(J11,$C$6:$H$6,0)) -> 45004

Sheet PIVOTBY
C4: Revenue
C6: Product | D6: Branch | E6: Net Sales
C7: Motherboard | D7: Pasay | E7: 150000 | G7: {=_xlfn.PIVOTBY(C7:C25,D7:D25,E7:E25,_xleta.SUM)} | H7: Mandaluyong | I7: Market- Market | J7: Pasay | K7: Total
C8: Motherboard | D8: Mandaluyong | E8: 280000 | G8: CPU | H8: 111111 | I8: 5000 | J8: 867000 | K8: 983111
C9: Power Supply | D9: Pasay | E9: 170000 | G9: Motherboard | H9: 280000 | I9: 699000 | J9: 150000 | K9: 1129000
C10: Motherboard | D10: Market- Market | E10: 99000 | G10: Power Supply | H10: 87000 | I10: 99000 | J10: 170000 | K10: 356000
C11: RAM | D11: Mandaluyong | E11: 450000 | G11: RAM | H11: 505000 | I11: 5400 | J11: 90000 | K11: 600400
C12: Motherboard | D12: Market- Market | E12: 600000 | G12: RGB fans | H12: 985600 | I12: 3400 | J12: 1211 | K12: 990211
C13: CPU | D13: Pasay | E13: 780000 | G13: Total | H13: 1968711 | I13: 811800 | J13: 1278211 | K13: 4058722
C14: RGB fans | D14: Mandaluyong | E14: 980000
C15: Power Supply | D15: Mandaluyong | E15: 87000
C16: Power Supply | D16: Market- Market | E16: 99000
C17: RAM | D17: Market- Market | E17: 5400
C18: RAM | D18: Pasay | E18: 90000
C19: RAM | D19: Mandaluyong | E19: 55000
C20: CPU | D20: Mandaluyong | E20: 111111
C21: CPU | D21: Pasay | E21: 87000
C22: CPU | D22: Market- Market | E22: 5000
C23: RGB fans | D23: Market- Market | E23: 3400
C24: RGB fans | D24: Mandaluyong | E24: 5600
C25: RGB fans | D25: Pasay | E25: 1211

Sheet FILTERFUNCTION
B4: Inventory List | E4: Available Stocks | H4: Zero Stocks
B6: Product | C6: Qty | E6: Product | F6: Qty | H6: Product | I6: Qty
B7: Motherboard | C7: 0 | E7: {=_xlfn._xlws.FILTER(B7:C22,C7:C22>0)} -> Power Supply | F7: 110 | H7: {=_xlfn._xlws.FILTER(B7:C22,C7:C22=0,"")} -> Motherboard | I7: 0
B8: GPU | C8: 0 | E8: RAM | F8: 1341 | H8: GPU | I8: 0
B9: Power Supply | C9: 110 | E9: CPU | F9: 22 | H9: CPU Cooler | I9: 0
B10: RAM | C10: 1341 | E10: RGB fans | F10: 112
B11: CPU | C11: 22 | E11: Case | F11: 66
B12: RGB fans | C12: 112 | E12: Mechanical Keyboard | F12: 200
B13: CPU Cooler | C13: 0 | E13: ROG mouse | F13: 340
B14: Case | C14: 66 | E14: Mouse pad | F14: 200
B15: Mechanical Keyboard | C15: 200 | E15: ROG headphone | F15: 160
B16: ROG mouse | C16: 340 | E16: Corsair chair | F16: 30
B17: Mouse pad | C17: 200 | E17: Gaming Mic | F17: 120
B18: ROG headphone | C18: 160 | E18: Digital Clock | F18: 300
B19: Corsair chair | C19: 30 | E19: RGB speaker | F19: 260
B20: Gaming Mic | C20: 120
B21: Digital Clock | C21: 300
B22: RGB speaker | C22: 260
